LICENSE
README.md
pyproject.toml
setup.cfg
setup.py
dolphinlog/__init__.py
dolphinlog/__main__.py
dolphinlog/qsodata.py
dolphinlog/version.py
dolphinlog.egg-info/PKG-INFO
dolphinlog.egg-info/SOURCES.txt
dolphinlog.egg-info/dependency_links.txt
dolphinlog.egg-info/entry_points.txt
dolphinlog.egg-info/top_level.txt