Metadata-Version: 2.1
Name: dolphinlog
Version: 0.2.9
Summary: Yet another HAM radio logger using SQLite with ADIF-3 export support.
Home-page: https://github.com/xaratustrah/dolphinlog
Author: xaratustrah
License: GPLv3
Keywords: HAM,Logging,Amateur Radio,QSO
Classifier: Environment :: Console
Classifier: Programming Language :: Python :: 3 :: Only
Classifier: License :: OSI Approved :: GNU General Public License v3 (GPLv3)
Classifier: Natural Language :: English
Classifier: Operating System :: OS Independent
Classifier: Topic :: Communications :: Ham Radio
Requires-Python: <4,>=3.7
License-File: LICENSE
